mcp_server.py
run_mcp.py
bin/robotframework-mcp.js
node_modules/accepts/HISTORY.md
node_modules/accepts/LICENSE
node_modules/accepts/README.md
node_modules/accepts/index.js
node_modules/accepts/package.json
node_modules/array-flatten/LICENSE
node_modules/array-flatten/README.md
node_modules/array-flatten/array-flatten.js
node_modules/array-flatten/package.json
node_modules/body-parser/HISTORY.md
node_modules/body-parser/LICENSE
node_modules/body-parser/README.md
node_modules/body-parser/SECURITY.md
node_modules/body-parser/index.js
node_modules/body-parser/package.json
node_modules/body-parser/lib/read.js
node_modules/body-parser/lib/types/json.js
node_modules/body-parser/lib/types/raw.js
node_modules/body-parser/lib/types/text.js
node_modules/body-parser/lib/types/urlencoded.js
node_modules/bytes/History.md
node_modules/bytes/LICENSE
node_modules/bytes/Readme.md
node_modules/bytes/index.js
node_modules/bytes/package.json
node_modules/call-bind-apply-helpers/CHANGELOG.md
node_modules/call-bind-apply-helpers/LICENSE
node_modules/call-bind-apply-helpers/README.md
node_modules/call-bind-apply-helpers/actualApply.js
node_modules/call-bind-apply-helpers/applyBind.js
node_modules/call-bind-apply-helpers/functionApply.js
node_modules/call-bind-apply-helpers/functionCall.js
node_modules/call-bind-apply-helpers/index.js
node_modules/call-bind-apply-helpers/package.json
node_modules/call-bind-apply-helpers/reflectApply.js
node_modules/call-bind-apply-helpers/tsconfig.json
node_modules/call-bind-apply-helpers/test/index.js
node_modules/call-bound/CHANGELOG.md
node_modules/call-bound/LICENSE
node_modules/call-bound/README.md
node_modules/call-bound/index.js
node_modules/call-bound/package.json
node_modules/call-bound/tsconfig.json
node_modules/call-bound/test/index.js
node_modules/child_process/README.md
node_modules/child_process/package.json
node_modules/content-disposition/HISTORY.md
node_modules/content-disposition/LICENSE
node_modules/content-disposition/README.md
robotframework_mcp-1.2.0.dist-info/licenses/LICENSE
robotframework_mcp-1.2.0.dist-info/METADATA
robotframework_mcp-1.2.0.dist-info/WHEEL
robotframework_mcp-1.2.0.dist-info/entry_points.txt
robotframework_mcp-1.2.0.dist-info/top_level.txt
robotframework_mcp-1.2.0.dist-info/RECORD
