Metadata-Version: 2.4
Name: robotframework-mcp
Version: 1.2.0
Summary: Robot Framework MCP Server with SeleniumLibrary support for AI-powered test automation
Author-email: Meenu Rani <meenu.rani@sourcefuse.com>
Maintainer-email: Meenu Rani <meenu.rani@sourcefuse.com>
License: MIT
Project-URL: Homepage, https://github.com/sourcefuse/robotframework-MCP
Project-URL: Repository, https://github.com/sourcefuse/robotframework-MCP.git
Project-URL: Issues, https://github.com/sourcefuse/robotframework-MCP/issues
Keywords: mcp,selenium,testing,robot-framework,automation,ai,code-generation,web-testing
Classifier: Development Status :: 4 - Beta
Classifier: Intended Audience :: Developers
Classifier: Operating System :: OS Independent
Classifier: Programming Language :: Python :: 3
Classifier: Programming Language :: Python :: 3.10
Classifier: Programming Language :: Python :: 3.11
Classifier: Programming Language :: Python :: 3.12
Classifier: Programming Language :: Python :: 3.13
Classifier: Topic :: Software Development :: Testing
Classifier: Topic :: Software Development :: Quality Assurance
Classifier: Framework :: Robot Framework
Requires-Python: >=3.10
License-File: LICENSE
Requires-Dist: mcp>=1.0.0
Requires-Dist: robotframework>=6.0
Requires-Dist: selenium>=4.0.0
Requires-Dist: robotframework-seleniumlibrary>=6.0
Provides-Extra: dev
Requires-Dist: build; extra == "dev"
Requires-Dist: twine; extra == "dev"
Requires-Dist: pytest; extra == "dev"
Requires-Dist: black; extra == "dev"
Requires-Dist: flake8; extra == "dev"
Dynamic: license-file
